executorlib/__init__.py
executorlib/_version.py
executorlib/api.py
executorlib/backend/__init__.py
executorlib/backend/cache_parallel.py
executorlib/backend/cache_serial.py
executorlib/backend/interactive_parallel.py
executorlib/backend/interactive_serial.py
executorlib/executor/__init__.py
executorlib/executor/base.py
executorlib/executor/flux.py
executorlib/executor/single.py
executorlib/executor/slurm.py
executorlib/standalone/__init__.py
executorlib/standalone/batched.py
executorlib/standalone/command.py
executorlib/standalone/error.py
executorlib/standalone/hdf.py
executorlib/standalone/inputcheck.py
executorlib/standalone/queue.py
executorlib/standalone/scheduler.py
executorlib/standalone/select.py
executorlib/standalone/serialize.py
executorlib/standalone/interactive/__init__.py
executorlib/standalone/interactive/arguments.py
executorlib/standalone/interactive/backend.py
executorlib/standalone/interactive/communication.py
executorlib/standalone/interactive/spawner.py
executorlib/task_scheduler/__init__.py
executorlib/task_scheduler/base.py
executorlib/task_scheduler/file/__init__.py
executorlib/task_scheduler/file/backend.py
executorlib/task_scheduler/file/shared.py
executorlib/task_scheduler/file/spawner_pysqa.py
executorlib/task_scheduler/file/spawner_subprocess.py
executorlib/task_scheduler/file/task_scheduler.py
executorlib/task_scheduler/interactive/__init__.py
executorlib/task_scheduler/interactive/blockallocation.py
executorlib/task_scheduler/interactive/dependency.py
executorlib/task_scheduler/interactive/dependency_plot.py
executorlib/task_scheduler/interactive/onetoone.py
executorlib/task_scheduler/interactive/shared.py
executorlib/task_scheduler/interactive/spawner_flux.py
executorlib/task_scheduler/interactive/spawner_pysqa.py
executorlib/task_scheduler/interactive/spawner_slurm.py
executorlib-1.7.4.dist-info/METADATA
executorlib-1.7.4.dist-info/WHEEL
executorlib-1.7.4.dist-info/licenses/LICENSE
executorlib-1.7.4.dist-info/RECORD
