Metadata-Version: 2.4
Name: executorlib
Version: 1.7.4
Summary: Up-scale python functions for high performance computing (HPC) with executorlib.
Project-URL: Homepage, https://github.com/pyiron/executorlib
Project-URL: Documentation, https://executorlib.readthedocs.io
Project-URL: Repository, https://github.com/pyiron/executorlib
Author-email: Jan Janssen <janssen@lanl.gov>
License: BSD 3-Clause License
License-File: LICENSE
Keywords: executor,flux-framework,high performance computing,hpc,slurm,task scheduler
Classifier: Development Status :: 5 - Production/Stable
Classifier: Intended Audience :: Science/Research
Classifier: License :: OSI Approved :: BSD License
Classifier: Operating System :: OS Independent
Classifier: Programming Language :: Python :: 3.10
Classifier: Programming Language :: Python :: 3.11
Classifier: Programming Language :: Python :: 3.12
Classifier: Programming Language :: Python :: 3.13
Classifier: Topic :: Scientific/Engineering :: Physics
Requires-Python: <3.14,>3.9
Requires-Dist: cloudpickle<=3.1.2,>=2.0.0
Requires-Dist: pyzmq<=27.1.0,>=25.0.0
Provides-Extra: all
Requires-Dist: h5py<=3.15.1,>=3.6.0; extra == 'all'
Requires-Dist: ipython<=9.9.0,>=7.33.0; extra == 'all'
Requires-Dist: mpi4py<=4.1.1,>=3.1.4; extra == 'all'
Requires-Dist: networkx<=3.6.1,>=2.8.8; extra == 'all'
Requires-Dist: pygraphviz<=1.14,>=1.10; extra == 'all'
Requires-Dist: pysqa==0.3.3; extra == 'all'
Provides-Extra: cache
Requires-Dist: h5py<=3.15.1,>=3.6.0; extra == 'cache'
Provides-Extra: cluster
Requires-Dist: h5py<=3.15.1,>=3.6.0; extra == 'cluster'
Requires-Dist: pysqa==0.3.3; extra == 'cluster'
Provides-Extra: graph
Requires-Dist: networkx<=3.6.1,>=2.8.8; extra == 'graph'
Requires-Dist: pygraphviz<=1.14,>=1.10; extra == 'graph'
Provides-Extra: graphnotebook
Requires-Dist: ipython<=9.9.0,>=7.33.0; extra == 'graphnotebook'
Requires-Dist: networkx<=3.6.1,>=2.8.8; extra == 'graphnotebook'
Requires-Dist: pygraphviz<=1.14,>=1.10; extra == 'graphnotebook'
Provides-Extra: mpi
Requires-Dist: mpi4py<=4.1.1,>=3.1.4; extra == 'mpi'
